klak/__init__.py
klak/cli.py
klak/klak.py
klak-0.4.3.dist-info/entry_points.txt
klak-0.4.3.dist-info/LICENSE
klak-0.4.3.dist-info/WHEEL
klak-0.4.3.dist-info/METADATA
klak-0.4.3.dist-info/RECORD
