Metadata-Version: 2.1
Name: klak
Version: 0.4.3
Summary: Klak provides the ergonoics of a project Makefile with the ease of Python and power of Click.
Home-page: https://github.com/aubricus/klak
License: MIT
Keywords: klak,automation
Author: Aubrey Taylor
Author-email: aubricus+klak@gmail.com
Requires-Python: >=3.5,<4.0
Classifier: Development Status :: 2 - Pre-Alpha
Classifier: Intended Audience :: Developers
Classifier: License :: OSI Approved :: MIT License
Classifier: Natural Language :: English
Classifier: Programming Language :: Python :: 3
Classifier: Programming Language :: Python :: 3.5
Classifier: Programming Language :: Python :: 3.6
Classifier: Programming Language :: Python :: 3.7
Requires-Dist: click (>=7.0,<8.0)
Project-URL: Documentation, https://github.com/aubricus/klak
Project-URL: Repository, https://github.com/aubricus/klak
